neo_python_rpc-0.2.1.dist-info/METADATA
neo_python_rpc-0.2.1.dist-info/RECORD
neo_python_rpc-0.2.1.dist-info/WHEEL
neo_python_rpc-0.2.1.dist-info/top_level.txt
neorpc/Client.py
neorpc/Settings.py
neorpc/__init__.py
